barely_json/__init__.py
barely_lb_json-0.1.1.dist-info/LICENSE
barely_lb_json-0.1.1.dist-info/METADATA
barely_lb_json-0.1.1.dist-info/WHEEL
barely_lb_json-0.1.1.dist-info/top_level.txt
barely_lb_json-0.1.1.dist-info/RECORD
